setup.py
pytreecat.egg-info/PKG-INFO
pytreecat.egg-info/SOURCES.txt
pytreecat.egg-info/dependency_links.txt
pytreecat.egg-info/entry_points.txt
pytreecat.egg-info/requires.txt
pytreecat.egg-info/top_level.txt
treecat/__init__.py
treecat/__init__.pyc
treecat/__init__.pyo
treecat/__main__.py
treecat/__main__.pyc
treecat/config.py
treecat/config.pyc
treecat/config.pyo
treecat/e2e_test.py
treecat/format.py
treecat/format.pyc
treecat/format.pyo
treecat/format_test.py
treecat/generate.py
treecat/generate.pyc
treecat/main_test.py
treecat/plotting.py
treecat/plotting.pyc
treecat/profile.py
treecat/profile.pyc
treecat/profile.pyo
treecat/profile_test.py
treecat/serving.py
treecat/serving.pyc
treecat/serving.pyo
treecat/serving_test.py
treecat/structure.py
treecat/structure.pyc
treecat/structure.pyo
treecat/structure_test.py
treecat/svgpan.js
treecat/testutil.py
treecat/testutil.pyc
treecat/testutil.pyo
treecat/training.py
treecat/training.pyc
treecat/training.pyo
treecat/training_test.py
treecat/util.py
treecat/util.pyc
treecat/util.pyo
treecat/util_test.py
treecat/validate.py
treecat/validate.pyc
treecat/validate_test.py