Metadata-Version: 1.1
Name: pytreecat
Version: 0.1.9
Summary: A Bayesian latent tree model of multivariate multinomial data
Home-page: https://github.com/posterior/treecat
Author: Fritz Obermeyer
Author-email: fritz.obermeyer@gmail.com
License: Apache License 2.0
Platform: UNKNOWN
Classifier: Development Status :: 3 - Alpha
Classifier: Intended Audience :: Developers
Classifier: Intended Audience :: Science/Research
Classifier: License :: OSI Approved :: Apache Software License
Classifier: Operating System :: MacOS :: MacOS X
Classifier: Operating System :: Microsoft :: Windows
Classifier: Operating System :: POSIX :: Linux
Classifier: Programming Language :: Python :: 2.7
Classifier: Programming Language :: Python :: 3.5
Classifier: Topic :: Scientific/Engineering :: Information Analysis
